epics_linter/__init__.py
epics_linter/__main__.py
epics_linter/common.py
epics_linter/db.py
epics_linter/linter.py
epics_linter/grammars/db.lark
epics_linter-0.0.2.dist-info/LICENSE
epics_linter-0.0.2.dist-info/METADATA
epics_linter-0.0.2.dist-info/WHEEL
epics_linter-0.0.2.dist-info/top_level.txt
epics_linter-0.0.2.dist-info/RECORD
